segmentation/__init__.py
segmentation/predict.py
segmentation/scrach.py
segmentation/trainer.py
segmentation/data_loader/__init__.py
segmentation/data_loader/segmentation_dataset.py
segmentation/data_loader/transform.py
segmentation/encoders/__init__.py
segmentation/encoders/mobilenet.py
segmentation/encoders/resnet.py
segmentation/encoders/squeeze_extractor.py
segmentation/encoders/vgg.py
segmentation/models/__init__.py
segmentation/models/all_models.py
segmentation/models/fcn16.py
segmentation/models/fcn32.py
segmentation/models/fcn8.py
segmentation/models/model_utils.py
segmentation/models/pspnet.py
segmentation/models/unet.py
segmentation/test/__init__.py
segmentation/test/scrach.py
util/__init__.py
util/checkpoint.py
util/imshow.py
util/logger.py
util/validation.py
seg_torch-0.1.7.dist-info/LICENSE
seg_torch-0.1.7.dist-info/METADATA
seg_torch-0.1.7.dist-info/WHEEL
seg_torch-0.1.7.dist-info/top_level.txt
seg_torch-0.1.7.dist-info/RECORD
