Metadata-Version: 2.1
Name: seg-torch
Version: 0.1.7
Summary: Semantic Segmentation with Pytorch
Home-page: https://github.com/IanTaehoonYoo/semantic-segmentation-pytorch
Author: Ian Yoo
Author-email: thyoostar@gmail.com
License: MIT
Platform: any
Classifier: License :: OSI Approved :: MIT License
Requires-Dist: torch (>=1.5.0)
Requires-Dist: torchvision (>=0.5.0)
Requires-Dist: tensorboardX (>=2.0opencv-python)
Requires-Dist: tqdm
Provides-Extra: tensorflow
Requires-Dist: tensorflow ; extra == 'tensorflow'
